uparse_client/__init__.py
uparse_client/_client.py
uparse_client/_constants.py
uparse_client/_types.py
uparse_client/uparse.py
uparse_client/utils.py
uparseconnect-0.0.4.dist-info/METADATA
uparseconnect-0.0.4.dist-info/WHEEL
uparseconnect-0.0.4.dist-info/RECORD
